evennia/VERSION.txt
evennia/VERSION_REQS.txt
evennia/__init__.py
evennia/__main__.py
evennia/settings_default.py
evennia/accounts/__init__.py
evennia/accounts/accounts.py
evennia/accounts/bots.py
evennia/accounts/manager.py
evennia/accounts/models.py
evennia/accounts/tests.py
evennia/accounts/migrations/0001_initial.py
evennia/accounts/migrations/0002_move_defaults.py
evennia/accounts/migrations/0003_auto_20150209_2234.py
evennia/accounts/migrations/0004_auto_20150403_2339.py
evennia/accounts/migrations/0005_auto_20160905_0902.py
evennia/accounts/migrations/0006_auto_20170606_1731.py
evennia/accounts/migrations/0007_copy_player_to_account.py
evennia/accounts/migrations/0008_auto_20190128_1820.py
evennia/accounts/migrations/0009_auto_20191025_0831.py
evennia/accounts/migrations/0010_auto_20210520_2137.py
evennia/accounts/migrations/0011_convert_contrib_typeclass_paths.py
evennia/accounts/migrations/0012_defaultaccount_alter_accountdb_id_account_bot_and_more.py
evennia/accounts/migrations/__init__.py
evennia/commands/__init__.py
evennia/commands/cmdhandler.py
evennia/commands/cmdparser.py
evennia/commands/cmdset.py
evennia/commands/cmdsethandler.py
evennia/commands/command.py
evennia/commands/tests.py
evennia/commands/_trial_temp/_trial_marker
evennia/commands/default/__init__.py
evennia/commands/default/account.py
evennia/commands/default/admin.py
evennia/commands/default/batchprocess.py
evennia/commands/default/building.py
evennia/commands/default/cmdset_account.py
evennia/commands/default/cmdset_character.py
evennia/commands/default/cmdset_session.py
evennia/commands/default/cmdset_unloggedin.py
evennia/commands/default/comms.py
evennia/commands/default/general.py
evennia/commands/default/help.py
evennia/commands/default/muxcommand.py
evennia/commands/default/syscommands.py
evennia/commands/default/system.py
evennia/commands/default/tests.py
evennia/commands/default/unloggedin.py
evennia/comms/__init__.py
evennia/comms/comms.py
evennia/comms/managers.py
evennia-5.0.0.dist-info/licenses/LICENSE.txt
evennia-5.0.0.dist-info/METADATA
evennia-5.0.0.dist-info/WHEEL
evennia-5.0.0.dist-info/entry_points.txt
evennia-5.0.0.dist-info/top_level.txt
evennia-5.0.0.dist-info/RECORD
