Metadata-Version: 2.4
Name: evennia
Version: 5.0.0
Summary: A full-featured toolkit and server for text-based multiplayer games (MUDs, MU*, etc).
Maintainer-email: Griatch <griatch@gmail.com>
License: BSD
Project-URL: Homepage, https://www.evennia.com
Project-URL: Github, https://github.com/evennia/evennia
Project-URL: Documentation, https://www.evennia.com/docs/latest/index.html
Project-URL: Live Demo, https://demo.evennia.com/
Project-URL: Forums, https://github.com/evennia/evennia/discussions
Project-URL: Discord, https://discord.gg/AJJpcRUhtF
Project-URL: Dev Blog, https://www.evennia.com/devblog/index.html
Project-URL: Game Index, http://games.evennia.com
Project-URL: Issue tracker, https://github.com/evennia/evennia/issues
Project-URL: Patreon, https://www.patreon.com/griatch
Keywords: MUD,MUSH,MUX,MMO,text-only,multiplayer,online,rpg,game,engine,framework,text,adventure,telnet,websocket,blind,accessible,ascii,utf-8,terminal,online,server,beginner,tutorials
Classifier: Programming Language :: Python :: 3 :: Only
Classifier: Programming Language :: Python :: 3.11
Classifier: Programming Language :: Python :: 3.12
Classifier: Programming Language :: Python :: 3.13
Classifier: Programming Language :: JavaScript
Classifier: Development Status :: 5 - Production/Stable
Classifier: License :: OSI Approved :: BSD License
Classifier: Environment :: Console
Classifier: Environment :: Web Environment
Classifier: Framework :: Django
Classifier: Framework :: Twisted
Classifier: Intended Audience :: Developers
Classifier: Intended Audience :: Education
Classifier: Operating System :: MacOS
Classifier: Operating System :: Microsoft :: Windows
Classifier: Operating System :: POSIX :: Linux
Classifier: Topic :: Database
Classifier: Topic :: Education
Classifier: Topic :: Games/Entertainment :: Multi-User Dungeons (MUD)
Classifier: Topic :: Games/Entertainment :: Puzzle Games
Classifier: Topic :: Games/Entertainment :: Role-Playing
Classifier: Topic :: Games/Entertainment :: Simulation
Classifier: Topic :: Software Development :: Libraries :: Application Frameworks
Classifier: Topic :: Internet :: WWW/HTTP :: WSGI :: Server
Requires-Python: >=3.11
License-File: LICENSE.txt
Requires-Dist: legacy-cgi; python_version >= "3.13"
Requires-Dist: django<5.3,>=5.2
Requires-Dist: twisted<25,>=24.11.0
Requires-Dist: pytz>=2022.6
Requires-Dist: djangorestframework<3.15,>=3.14
Requires-Dist: pyyaml>=6.0
Requires-Dist: django-filter==2.4
Requires-Dist: django-sekizai==2.0.0
Requires-Dist: inflect>=5.2.0
Requires-Dist: autobahn<21.0.0,>=20.7.1
Requires-Dist: lunr==0.7.0.post1
Requires-Dist: simpleeval<=1.0
Requires-Dist: uritemplate==4.1.1
Requires-Dist: tzdata>=2022.6
Requires-Dist: mock>=4.0.3
Requires-Dist: model_mommy>=2.0
Requires-Dist: anything==0.2.1
Requires-Dist: black>=22.6
Requires-Dist: isort>=5.10
Requires-Dist: parameterized==0.9.0
Provides-Extra: extra
Requires-Dist: cryptography>=2.8; extra == "extra"
Requires-Dist: pyasn1>=0.4.8; extra == "extra"
Requires-Dist: bcrypt>=3.1.7; extra == "extra"
Requires-Dist: pyopenssl>=19.1; extra == "extra"
Requires-Dist: service_identity>=18.1.0; extra == "extra"
Requires-Dist: boto3>=1.4.4; extra == "extra"
Requires-Dist: botocore>=1.15; extra == "extra"
Requires-Dist: jupyter>=1.0.0; extra == "extra"
Requires-Dist: ipython>=7.19.0; extra == "extra"
Requires-Dist: django-extensions>=3.1.0; extra == "extra"
Requires-Dist: scipy==1.15.1; extra == "extra"
Requires-Dist: gitpython>=3.1.27; extra == "extra"
Dynamic: license-file
